cgs/__init__.py
cgs/__main__.py
cgs/cli.py
cgs/create.py
cgs/delete.py
cgs/fullall.py
cgs/updateres.py
cgs/utils.py
cgs-0.1.9.dist-info/LICENSE
cgs-0.1.9.dist-info/METADATA
cgs-0.1.9.dist-info/WHEEL
cgs-0.1.9.dist-info/entry_points.txt
cgs-0.1.9.dist-info/top_level.txt
cgs-0.1.9.dist-info/RECORD
