Metadata-Version: 2.1
Name: cgs
Version: 0.1.9
Summary: Create & update reservations at Cégep Sainte-Foy gym with this simple api.
Home-page: https://github.com/Msa360/cgs-csfoy-gym
Author: msa360
Author-email: arnaud25@icloud.com
License: MIT
Classifier: Programming Language :: Python :: 3
Classifier: Programming Language :: Python :: 3.9
Classifier: Operating System :: OS Independent
Classifier: License :: OSI Approved :: MIT License
License-File: LICENSE
Requires-Dist: beautifulsoup4 (>=4.10.0)
Requires-Dist: certifi (>=2021.10.8)
Requires-Dist: charset-normalizer (>=2.0.12)
Requires-Dist: idna (>=3.3)
Requires-Dist: requests (>=2.27.1)
Requires-Dist: soupsieve (>=2.3.1)
Requires-Dist: urllib3 (>=1.26.8)
